sdl_x/__init__.py
sdl_x/active.py
sdl_x/functions.py
sdl_x/gradient.py
sdl_x/layer.py
sdl_x/lose.py
sdl_x/mnist.py
sdl_x/net.py
sdl_x/update.py
sdl_x-0.0.2.dist-info/METADATA
sdl_x-0.0.2.dist-info/WHEEL
sdl_x-0.0.2.dist-info/top_level.txt
sdl_x-0.0.2.dist-info/RECORD
