Metadata-Version: 2.1
Name: sdl-x
Version: 0.0.2
Summary: collected simple deep learning functions
Home-page: UNKNOWN
Author: huhuang03
License: UNKNOWN
Platform: UNKNOWN
Requires-Dist: numpy
